xontrib_uvox/__init__.py
xontrib_uvox/utils.py
xontrib_uvox/uvox.py
xontrib_uvox/uvoxapi.py
xontrib_uvox-0.1.1.dist-info/licenses/LICENCE.md
xontrib_uvox-0.1.1.dist-info/METADATA
xontrib_uvox-0.1.1.dist-info/WHEEL
xontrib_uvox-0.1.1.dist-info/entry_points.txt
xontrib_uvox-0.1.1.dist-info/top_level.txt
xontrib_uvox-0.1.1.dist-info/RECORD
