Metadata-Version: 2.4
Name: xontrib-uvox
Version: 0.1.1
Summary: Python virtual environment manager for xonsh.
Author-email: Morgan Grobol <morgan.grobol@tuta.com>
License-Expression: MIT
Project-URL: Homepage, https://github.com/LoicGrobol/xontrib-uvox
Project-URL: Documentation, https://github.com/LoicGrobol/xontrib-uvox/blob/main/README.md
Project-URL: Code, https://github.com/LoicGrobol/xontrib-uvox
Project-URL: Issue tracker, https://github.com/LoicGrobol/xontrib-uvox/issues
Platform: any
Classifier: Programming Language :: Python :: 3
Classifier: Operating System :: OS Independent
Classifier: Topic :: System :: Shells
Classifier: Topic :: System :: System Shells
Classifier: Topic :: Terminals
Requires-Python: >=3.11
License-File: LICENCE.md
Requires-Dist: xonsh>=0.12.5
Requires-Dist: uv
Provides-Extra: dev
Requires-Dist: pytest>=7.0; extra == "dev"
Dynamic: license-file
